odoo/addons/partner_deduplicate_by_ref/README.rst
odoo/addons/partner_deduplicate_by_ref/__init__.py
odoo/addons/partner_deduplicate_by_ref/__manifest__.py
odoo/addons/partner_deduplicate_by_ref/i18n/ar.po
odoo/addons/partner_deduplicate_by_ref/i18n/bs.po
odoo/addons/partner_deduplicate_by_ref/i18n/cs.po
odoo/addons/partner_deduplicate_by_ref/i18n/de.po
odoo/addons/partner_deduplicate_by_ref/i18n/en_GB.po
odoo/addons/partner_deduplicate_by_ref/i18n/es.po
odoo/addons/partner_deduplicate_by_ref/i18n/es_CR.po
odoo/addons/partner_deduplicate_by_ref/i18n/es_EC.po
odoo/addons/partner_deduplicate_by_ref/i18n/es_MX.po
odoo/addons/partner_deduplicate_by_ref/i18n/et.po
odoo/addons/partner_deduplicate_by_ref/i18n/fr.po
odoo/addons/partner_deduplicate_by_ref/i18n/gl.po
odoo/addons/partner_deduplicate_by_ref/i18n/hr.po
odoo/addons/partner_deduplicate_by_ref/i18n/hu.po
odoo/addons/partner_deduplicate_by_ref/i18n/it.po
odoo/addons/partner_deduplicate_by_ref/i18n/ja.po
odoo/addons/partner_deduplicate_by_ref/i18n/lt.po
odoo/addons/partner_deduplicate_by_ref/i18n/lv.po
odoo/addons/partner_deduplicate_by_ref/i18n/mk.po
odoo/addons/partner_deduplicate_by_ref/i18n/mn.po
odoo/addons/partner_deduplicate_by_ref/i18n/nb.po
odoo/addons/partner_deduplicate_by_ref/i18n/nl.po
odoo/addons/partner_deduplicate_by_ref/i18n/nl_BE.po
odoo/addons/partner_deduplicate_by_ref/i18n/nl_NL.po
odoo/addons/partner_deduplicate_by_ref/i18n/partner_deduplicate_by_ref.pot
odoo/addons/partner_deduplicate_by_ref/i18n/pt.po
odoo/addons/partner_deduplicate_by_ref/i18n/pt_BR.po
odoo/addons/partner_deduplicate_by_ref/i18n/pt_PT.po
odoo/addons/partner_deduplicate_by_ref/i18n/ro.po
odoo/addons/partner_deduplicate_by_ref/i18n/ru.po
odoo/addons/partner_deduplicate_by_ref/i18n/sk.po
odoo/addons/partner_deduplicate_by_ref/i18n/sl.po
odoo/addons/partner_deduplicate_by_ref/i18n/sv.po
odoo/addons/partner_deduplicate_by_ref/i18n/th.po
odoo/addons/partner_deduplicate_by_ref/i18n/tr.po
odoo12_addon_partner_deduplicate_by_ref-12.0.1.0.0.99.dev5.dist-info/METADATA
odoo12_addon_partner_deduplicate_by_ref-12.0.1.0.0.99.dev5.dist-info/WHEEL
odoo12_addon_partner_deduplicate_by_ref-12.0.1.0.0.99.dev5.dist-info/top_level.txt
odoo12_addon_partner_deduplicate_by_ref-12.0.1.0.0.99.dev5.dist-info/RECORD
